AUTHORS
CHANGES
LICENSE
MANIFEST.in
Makefile
README.rst
TODO
setup.py
docs/Makefile
docs/conf.py
docs/features.rst
docs/index.rst
docs/make.bat
docs/todo.rst
docs/_static/README
docs/_static/webapp2_blue.png
docs/_static/webapp2_blue_small.png
docs/_static/webapp2_blue_tiny.png
docs/_templates/README
docs/_themes/webapp2/layout.html
docs/_themes/webapp2/pygapp2.py
docs/_themes/webapp2/theme.conf
docs/_themes/webapp2/static/gcode.css
docs/_themes/webapp2/static/webapp2.css
docs/api/extras.config.rst
docs/api/extras.i18n.rst
docs/api/extras.jinja2.rst
docs/api/extras.json.rst
docs/api/extras.local.rst
docs/api/extras.local_app.rst
docs/api/extras.mako.rst
docs/api/extras.routes.rst
docs/api/extras.securecookie.rst
docs/api/extras.security.rst
docs/api/extras.sessions.rst
docs/api/extras.sessions_memcache.rst
docs/api/extras.sessions_ndb.rst
docs/api/extras.users.rst
docs/api/index.rst
docs/api/webapp2.rst
docs/api/webapp2_extras/auth.rst
docs/api/webapp2_extras/i18n.rst
docs/api/webapp2_extras/jinja2.rst
docs/api/webapp2_extras/json.rst
docs/api/webapp2_extras/local.rst
docs/api/webapp2_extras/mako.rst
docs/api/webapp2_extras/routes.rst
docs/api/webapp2_extras/securecookie.rst
docs/api/webapp2_extras/security.rst
docs/api/webapp2_extras/sessions.rst
docs/api/webapp2_extras/appengine/sessions_memcache.rst
docs/api/webapp2_extras/appengine/sessions_ndb.rst
docs/api/webapp2_extras/appengine/users.rst
docs/api/webapp2_extras/appengine/auth/models.rst
docs/guide/app.rst
docs/guide/exceptions.rst
docs/guide/extras.rst
docs/guide/handlers.rst
docs/guide/index.rst
docs/guide/request.rst
docs/guide/response.rst
docs/guide/routing.rst
docs/guide/testing.rst
docs/tutorials/auth.rst
docs/tutorials/i18n.rst
docs/tutorials/index.rst
docs/tutorials/installing.packages.rst
docs/tutorials/marketplace.single.signon.rst
docs/tutorials/quickstart.nogae.rst
docs/tutorials/quickstart.rst
docs/tutorials/virtualenv.rst
docs/tutorials/gettingstarted/devenvironment.rst
webapp3.egg-info/PKG-INFO
webapp3.egg-info/SOURCES.txt
webapp3.egg-info/dependency_links.txt
webapp3.egg-info/not-zip-safe
webapp3.egg-info/requires.txt
webapp3.egg-info/top_level.txt
