Metadata-Version: 2.1
Name: webapp3
Version: 1.0.2
Summary: Taking Google App Engine's webapp to the next next level!
Home-page: UNKNOWN
Author: The Webapp3 Maintainers
Author-email: camille.tolsa@gmail.com
License: Apache Software License
Platform: any
Classifier: Development Status :: 5 - Production/Stable
Classifier: Environment :: Web Environment
Classifier: Intended Audience :: Developers
Classifier: License :: OSI Approved :: Apache Software License
Classifier: Operating System :: OS Independent
Classifier: Programming Language :: Python
Classifier: Topic :: Internet :: WWW/HTTP :: Dynamic Content
Classifier: Topic :: Software Development :: Libraries :: Python Modules
Provides-Extra: extras
